qutlass/__init__.py
qutlass-0.0.0.dist-info/METADATA
qutlass-0.0.0.dist-info/WHEEL
qutlass-0.0.0.dist-info/top_level.txt
qutlass-0.0.0.dist-info/RECORD
