Metadata-Version: 2.4
Name: qutlass
Version: 0.0.0
Summary: Temp
License: MIT
Requires-Dist: numpy
